{
  "version": "1.1.0",
  "diagrams": [
    {
      "ordinal": 0,
      "scrollPosition": {
        "x": 0,
        "y": 0
      },
      "nodes": [
        {
          "location": {
            "x": 973.50074854312743,
            "y": 1572.8941883976449
          },
          "nodeIndex": "BORROWING_BASE_CONFIG_DAILY",
          "nodeLineageTag": "c24ef919-6f52-48f3-8054-bab887fd77fc",
          "size": {
            "height": 176,
            "width": 234
          },
          "zIndex": 0
        },
        {
          "location": {
            "x": 1680.3692952490028,
            "y": 1967.0049660699224
          },
          "nodeIndex": "CALENDAR",
          "nodeLineageTag": "d46911ea-ec7a-4bae-988d-3a42f565390d",
          "size": {
            "height": 300,
            "width": 234
          },
          "zIndex": 0
        },
        {
          "location": {
            "x": 4315.0403982560092,
            "y": 0
          },
          "nodeIndex": "CALENDAR_FULL",
          "nodeLineageTag": "eb9d8bac-832c-4eac-9f75-12f7b6c4f9a0",
          "size": {
            "height": 300,
            "width": 234
          },
          "zIndex": 0
        },
        {
          "location": {
            "x": 3189.6624763614591,
            "y": 2196.2020401236905
          },
          "nodeIndex": "CURRENT_SYSTEM_DATE",
          "nodeLineageTag": "9108c3b4-c0c0-45af-89d8-232fd8c2e60e",
          "size": {
            "height": 300,
            "width": 234
          },
          "zIndex": 0
        },
        {
          "location": {
            "x": 4733.2215060596245,
            "y": 50
          },
          "nodeIndex": "Data Dictionary",
          "nodeLineageTag": "15489998-3ce7-460d-8413-ca328a1a0758",
          "size": {
            "height": 200,
            "width": 234
          },
          "zIndex": 0
        },
        {
          "location": {
            "x": 1167.3355428654304,
            "y": 3989.1527837991989
          },
          "nodeIndex": "DATA_PROVIDER",
          "nodeLineageTag": "fdabc316-b735-4281-a6d2-2181f3c0f0bc",
          "size": {
            "height": 272,
            "width": 234
          },
          "zIndex": 0
        },
        {
          "location": {
            "x": 3618.3672531467628,
            "y": 2171.9087208722212
          },
          "nodeIndex": "GICS_MATRIX",
          "nodeLineageTag": "1d553be3-f503-42d6-8f34-22109928266d",
          "size": {
            "height": 248,
            "width": 234
          },
          "zIndex": 0
        },
        {
          "location": {
            "x": 1932.0455546604967,
            "y": 1967.0049660699224
          },
          "nodeIndex": "HOLDING",
          "nodeLineageTag": "a1f95dac-e64d-4c15-bbb4-b1f87a24138f",
          "size": {
            "height": 300,
            "width": 234
          },
          "zIndex": 0
        },
        {
          "location": {
            "x": 1471.4155993770828,
            "y": 2866.788978513795
          },
          "nodeIndex": "HOLDING_IBOXX",
          "nodeLineageTag": "cc86b28b-b1be-49ca-99be-682f78a6b2e7",
          "size": {
            "height": 300,
            "width": 234
          },
          "zIndex": 0
        },
        {
          "location": {
            "x": 1890.7842920136693,
            "y": 2894.7574168930141
          },
          "nodeIndex": "HOLDING_IBOXXS",
          "nodeLineageTag": "9e793c94-0ad6-4bfe-b1c8-9adaa98317f8",
          "size": {
            "height": 300,
            "width": 234
          },
          "zIndex": 0
        },
        {
          "location": {
            "x": 3058.1219051792214,
            "y": 3472.3517146242139
          },
          "nodeIndex": "HOLDING_IBOXXS_PLUS",
          "nodeLineageTag": "373ca740-9a19-4af1-8213-04d228abd54e",
          "size": {
            "height": 300,
            "width": 234
          },
          "zIndex": 0
        },
        {
          "location": {
            "x": 2216.6855032347057,
            "y": 2850.9442350953505
          },
          "nodeIndex": "HOLDING_MPSIF",
          "nodeLineageTag": "393a06cb-3908-4ab7-a267-7f20b5dbfb9f",
          "size": {
            "height": 300,
            "width": 234
          },
          "zIndex": 0
        },
        {
          "location": {
            "x": 735.477203765292,
            "y": 2744.2946363092387
          },
          "nodeIndex": "HOQ_INSTRUMENT_CHANGE",
          "nodeLineageTag": "15b8d296-f5f8-4faa-ab5a-7fc1313667f2",
          "size": {
            "height": 300,
            "width": 234
          },
          "zIndex": 0
        },
        {
          "location": {
            "x": 316.10851112870569,
            "y": 2619.6181563237005
          },
          "nodeIndex": "HOQ_LIFE_IS_GOOD",
          "nodeLineageTag": "cab8e8fc-07e9-4dea-8b7a-3d1a427aa7c3",
          "size": {
            "height": 296,
            "width": 234
          },
          "zIndex": 0
        },
        {
          "location": {
            "x": 1198.8053602120538,
            "y": 2803.019926277696
          },
          "nodeIndex": "HOQ_MESSAGE",
          "nodeLineageTag": "c3c55ac0-0c4a-4efe-936f-048d426d2988",
          "size": {
            "height": 300,
            "width": 234
          },
          "zIndex": 0
        },
        {
          "location": {
            "x": 3823.822129628913,
            "y": 3410.5695294786792
          },
          "nodeIndex": "HOQ_MESSAGE_INSTRUMENT_PIVOT",
          "nodeLineageTag": "c4ecb9fe-80a7-4767-99a8-0b90194bc250",
          "size": {
            "height": 296,
            "width": 234
          },
          "zIndex": 0
        },
        {
          "location": {
            "x": 1839.6655366992127,
            "y": 4500.8245612407909
          },
          "nodeIndex": "HOQ_MESSAGE_PRICE_PIVOT",
          "nodeLineageTag": "6115837a-26ac-4275-b105-343c3efb9607",
          "size": {
            "height": 200,
            "width": 234
          },
          "zIndex": 0
        },
        {
          "location": {
            "x": 2447.491706770184,
            "y": 2012.3097920499849
          },
          "nodeIndex": "HOQ_RATING_CHANGE",
          "nodeLineageTag": "9223c5c5-5e6f-4231-ad05-8f06b240f449",
          "size": {
            "height": 296,
            "width": 234
          },
          "zIndex": 0
        },
        {
          "location": {
            "x": 419.36869263658627,
            "y": 2258.9259436726525
          },
          "nodeIndex": "HOQ_RULE",
          "nodeLineageTag": "f9ae51be-b341-4dae-94bc-264357d3c73b",
          "size": {
            "height": 300,
            "width": 234
          },
          "zIndex": 0
        },
        {
          "location": {
            "x": 213.30952146732398,
            "y": 3687.1681356380732
          },
          "nodeIndex": "HOQ_RULE_SEVERITY",
          "nodeLineageTag": "9f9f1ea5-1cd3-48c2-bc92-c4eec5ca6e6e",
          "size": {
            "height": 272,
            "width": 234
          },
          "zIndex": 0
        },
        {
          "location": {
            "x": 0,
            "y": 2242.0774282130751
          },
          "nodeIndex": "HOQ_RULE_TYPE",
          "nodeLineageTag": "2ecd7111-8504-4586-bcc2-c66d36096dbd",
          "size": {
            "height": 272,
            "width": 234
          },
          "zIndex": 0
        },
        {
          "location": {
            "x": 1392.8694411797137,
            "y": 1733.650225926388
          },
          "nodeIndex": "INDEX_DELTA_DAILY",
          "nodeLineageTag": "30825ace-e35b-471b-8c50-7aeb412a94b0",
          "size": {
            "height": 248,
            "width": 234
          },
          "zIndex": 0
        },
        {
          "location": {
            "x": 2278.5498279662752,
            "y": 3202.2051320563141
          },
          "nodeIndex": "INSTRUMENT_EOD_PRICE_DAILY",
          "nodeLineageTag": "fb4d4fa1-d8dd-4053-a90b-0504ddecb9f3",
          "size": {
            "height": 300,
            "width": 234
          },
          "zIndex": 0
        },
        {
          "location": {
            "x": 2268.4885685284762,
            "y": 1481.6362734333361
          },
          "nodeIndex": "INSTRUMENT_EOD_PRICE_DAILY_CURRENT",
          "nodeLineageTag": "7b9b59ab-9968-47f1-99bd-1ca1c6c95c28",
          "size": {
            "height": 300,
            "width": 234
          },
          "zIndex": 0
        },
        {
          "location": {
            "x": 2874.2598987347892,
            "y": 2197.1261028035342
          },
          "nodeIndex": "INSTRUMENT_LIQUIDITY",
          "nodeLineageTag": "2aeee580-786e-4c6a-a7ca-7dec17b4d62b",
          "size": {
            "height": 300,
            "width": 234
          },
          "zIndex": 0
        },
        {
          "location": {
            "x": 2207.640617495646,
            "y": 1933.2539049126135
          },
          "nodeIndex": "INSTRUMENT_LIQUIDITY_PIVOT",
          "nodeLineageTag": "3d2df06b-5314-47a5-b6fb-bd18ab7f2ea7",
          "size": {
            "height": 296,
            "width": 234
          },
          "zIndex": 0
        },
        {
          "location": {
            "x": 2551.4282726157217,
            "y": 996.26758079674983
          },
          "nodeIndex": "INSTRUMENT_LIQUIDITY_SPGLOBAL",
          "nodeLineageTag": "3e6d36de-9e9b-4e84-8f7c-12d6a1579fc0",
          "size": {
            "height": 300,
            "width": 234
          },
          "zIndex": 0
        },
        {
          "location": {
            "x": 1661.4688803927897,
            "y": 3769.3521983192177
          },
          "nodeIndex": "INSTRUMENT_OF_INTEREST",
          "nodeLineageTag": "61e5f668-7869-4817-b711-253c192fd657",
          "size": {
            "height": 152,
            "width": 234
          },
          "zIndex": 0
        },
        {
          "location": {
            "x": 2310.1529846502553,
            "y": 3666.9157704980762
          },
          "nodeIndex": "INSTRUMENT_OFFICIAL_PRICE",
          "nodeLineageTag": "ca012a0f-0c51-4e07-b4d1-b5c61ef78e32",
          "size": {
            "height": 300,
            "width": 234
          },
          "zIndex": 0
        },
        {
          "location": {
            "x": 1392.8694411797137,
            "y": 1024.588857811048
          },
          "nodeIndex": "INSTRUMENT_PRICE",
          "nodeLineageTag": "98901ab7-99fd-40d0-b769-8084d63f4b05",
          "size": {
            "height": 300,
            "width": 234
          },
          "zIndex": 0
        },
        {
          "location": {
            "x": 1471.4155993770828,
            "y": 3244.5489652419856
          },
          "nodeIndex": "INSTRUMENT_PRICE_SPGLOBAL",
          "nodeLineageTag": "44fe1685-be0f-41cb-8d30-4a54b447a393",
          "size": {
            "height": 300,
            "width": 234
          },
          "zIndex": 0
        },
        {
          "location": {
            "x": 2929.1613267848643,
            "y": 4477.6881054315845
          },
          "nodeIndex": "INSTRUMENT_PRICE_SPGLOBAL_DISTINCT_IDENTIFIERS",
          "nodeLineageTag": "368dbcab-8ec0-49b1-a813-e8c6119abd4c",
          "size": {
            "height": 104,
            "width": 234
          },
          "zIndex": 0
        },
        {
          "location": {
            "x": 2779.6908977749254,
            "y": 1880.2068498221779
          },
          "nodeIndex": "INSTRUMENT_RATING",
          "nodeLineageTag": "8990d636-0133-4ed1-a3b3-01cef4e1b311",
          "size": {
            "height": 300,
            "width": 234
          },
          "zIndex": 0
        },
        {
          "location": {
            "x": 1052.0469067404965,
            "y": 3675.1273917496592
          },
          "nodeIndex": "INSTRUMENT_RATING_IBOXX",
          "nodeLineageTag": "5100edcd-1839-4065-8468-cbed8f6d80b3",
          "size": {
            "height": 300,
            "width": 234
          },
          "zIndex": 0
        },
        {
          "location": {
            "x": 2757.6935112976516,
            "y": 4040.465479280977
          },
          "nodeIndex": "INSTRUMENT_RATING_LEVPRO_MOODYS",
          "nodeLineageTag": "8d7e6529-d690-400c-a103-aaf81258b920",
          "size": {
            "height": 300,
            "width": 234
          },
          "zIndex": 0
        },
        {
          "location": {
            "x": 3474.7915811444645,
            "y": 2605.2774135088075
          },
          "nodeIndex": "INSTRUMENT_RATING_LEVPRO_SPGLOBAL",
          "nodeLineageTag": "5784d429-a4c3-46d4-a2f0-2a8eed231989",
          "size": {
            "height": 300,
            "width": 234
          },
          "zIndex": 0
        },
        {
          "location": {
            "x": 2638.7532125426351,
            "y": 3506.9507201584138
          },
          "nodeIndex": "INSTRUMENT_RATING_MOODYS",
          "nodeLineageTag": "d8ec9d95-da31-418a-af2d-c9d1f1a451da",
          "size": {
            "height": 300,
            "width": 234
          },
          "zIndex": 0
        },
        {
          "location": {
            "x": 2006.0729281386034,
            "y": 3607.4960183604062
          },
          "nodeIndex": "INSTRUMENT_RATING_MOODYS_WSO",
          "nodeLineageTag": "fa57b52b-7246-401d-9cf0-18c1d491f71c",
          "size": {
            "height": 300,
            "width": 234
          },
          "zIndex": 0
        },
        {
          "location": {
            "x": 566.87673055872392,
            "y": 3711.1060372103484
          },
          "nodeIndex": "INSTRUMENT_RATING_MPC_MOODYS",
          "nodeLineageTag": "21976686-1893-49aa-89d7-d44c35285dd3",
          "size": {
            "height": 300,
            "width": 234
          },
          "zIndex": 0
        },
        {
          "location": {
            "x": 3896.8592904523944,
            "y": 2925.2008368420929
          },
          "nodeIndex": "INSTRUMENT_RATING_MPC_SPGLOBAL",
          "nodeLineageTag": "c00ddd4b-ffff-4381-a5e9-6a3ee812562b",
          "size": {
            "height": 300,
            "width": 234
          },
          "zIndex": 0
        },
        {
          "location": {
            "x": 1988.60469839514,
            "y": 996.26758079674983
          },
          "nodeIndex": "INSTRUMENT_RATING_OFFICIAL",
          "nodeLineageTag": "0657684b-1110-4ed1-860b-42cf28f05136",
          "size": {
            "height": 300,
            "width": 234
          },
          "zIndex": 0
        },
        {
          "location": {
            "x": 2552.06643426798,
            "y": 3181.54707786149
          },
          "nodeIndex": "INSTRUMENT_RATING_SENTRY_MOODYS",
          "nodeLineageTag": "35aad337-0f75-4c87-851e-a5fb6fcdc2a2",
          "size": {
            "height": 300,
            "width": 234
          },
          "zIndex": 0
        },
        {
          "location": {
            "x": 3039.9462597048951,
            "y": 3992.3194127949982
          },
          "nodeIndex": "INSTRUMENT_RATING_SENTRY_SPGLOBAL",
          "nodeLineageTag": "546cd91a-4a16-40d2-ad45-69089afc37cb",
          "size": {
            "height": 300,
            "width": 234
          },
          "zIndex": 0
        },
        {
          "location": {
            "x": 3055.4228885078783,
            "y": 2539.0126717929788
          },
          "nodeIndex": "INSTRUMENT_RATING_SPGLOBAL",
          "nodeLineageTag": "d3964b40-2348-41ef-bc7f-6e2cd17967b9",
          "size": {
            "height": 300,
            "width": 234
          },
          "zIndex": 0
        },
        {
          "location": {
            "x": 1890.7842920136691,
            "y": 4015.4558686042046
          },
          "nodeIndex": "INSTRUMENT_RATING_SPGLOBAL_WSO",
          "nodeLineageTag": "64a73745-adff-4e7b-a954-96a597c4d2cc",
          "size": {
            "height": 300,
            "width": 234
          },
          "zIndex": 0
        },
        {
          "location": {
            "x": 2636.054195871292,
            "y": 2748.9411525098867
          },
          "nodeIndex": "INSTRUMENT_RISK_RANKING_DAILY",
          "nodeLineageTag": "53d63bc4-fa7d-4e3b-9e53-9642eee754d9",
          "size": {
            "height": 300,
            "width": 234
          },
          "zIndex": 0
        },
        {
          "location": {
            "x": 2454.8912060982029,
            "y": 2365.5755424587642
          },
          "nodeIndex": "INSTRUMENT_TS",
          "nodeLineageTag": "004f458a-5ec9-4de9-b40e-e3cf3c2f737b",
          "size": {
            "height": 300,
            "width": 234
          },
          "zIndex": 0
        },
        {
          "location": {
            "x": 2266.1137423430578,
            "y": 4637.6531557712487
          },
          "nodeIndex": "NEW_ISSUE",
          "nodeLineageTag": "8f9a970d-2ca0-46a8-953b-2842ffa36561",
          "size": {
            "height": 300,
            "width": 234
          },
          "zIndex": 0
        },
        {
          "location": {
            "x": 3477.4905978158076,
            "y": 3147.8804063337084
          },
          "nodeIndex": "OBJECT_TYPE",
          "nodeLineageTag": "88e66f5b-80ca-4256-a8c9-df57d4378f45",
          "size": {
            "height": 272,
            "width": 234
          },
          "zIndex": 0
        },
        {
          "location": {
            "x": 3055.4228885078783,
            "y": 2945.4739160002046
          },
          "nodeIndex": "ORDERS",
          "nodeLineageTag": "2fe5fff0-2e3b-4067-b2d1-8a97d57a3e25",
          "size": {
            "height": 300,
            "width": 234
          },
          "zIndex": 0
        },
        {
          "location": {
            "x": 1604.9027811081703,
            "y": 2381.4202858772087
          },
          "nodeIndex": "PNL",
          "nodeLineageTag": "8e11bb73-6fb6-4db1-af1b-52474169c09b",
          "size": {
            "height": 300,
            "width": 234
          },
          "zIndex": 0
        },
        {
          "location": {
            "x": 2024.2714737447568,
            "y": 2452.3736587065086
          },
          "nodeIndex": "PNL_ITD_DAILY",
          "nodeLineageTag": "d17ed5fe-1757-494e-a859-057b28d69519",
          "size": {
            "height": 300,
            "width": 234
          },
          "zIndex": 0
        },
        {
          "location": {
            "x": 1890.7842920136691,
            "y": 3283.9835056826314
          },
          "nodeIndex": "PNL_ITD_DAILY_IBOXXS",
          "nodeLineageTag": "087fb509-0443-4d90-815a-42af28681fc1",
          "size": {
            "height": 300,
            "width": 234
          },
          "zIndex": 0
        },
        {
          "location": {
            "x": 1812.2381338163002,
            "y": 1481.6362734333361
          },
          "nodeIndex": "PNL_ITD_DAILY_MPSIF",
          "nodeLineageTag": "1f4d74ad-2b02-4996-88ec-1bfbbf3498f0",
          "size": {
            "height": 300,
            "width": 234
          },
          "zIndex": 0
        },
        {
          "location": {
            "x": 1586.7042355020169,
            "y": 3942.2463395821351
          },
          "nodeIndex": "PORTFOLIO",
          "nodeLineageTag": "07f2d3fa-633b-4fae-b04b-fcc08b693530",
          "size": {
            "height": 300,
            "width": 234
          },
          "zIndex": 0
        },
        {
          "location": {
            "x": 750.03271735814178,
            "y": 4446.5214764357852
          },
          "nodeIndex": "PORTFOLIO_NAV_DAILY",
          "nodeLineageTag": "7f23fbe3-9591-49e2-b173-61e0c5431bd7",
          "size": {
            "height": 300,
            "width": 234
          },
          "zIndex": 0
        },
        {
          "location": {
            "x": 3474.7915811444645,
            "y": 3427.3077214768482
          },
          "nodeIndex": "RATING_MATRIX",
          "nodeLineageTag": "6f58e0fe-24a7-47e3-a23f-f98ffadf68e4",
          "size": {
            "height": 300,
            "width": 234
          },
          "zIndex": 0
        },
        {
          "location": {
            "x": 5151.40261386324,
            "y": 74
          },
          "nodeIndex": "Releases",
          "nodeLineageTag": "f1eafaa1-3258-45bd-a514-f95f9ca1579d",
          "size": {
            "height": 152,
            "width": 234
          },
          "zIndex": 0
        },
        {
          "location": {
            "x": 2338.3248186610654,
            "y": 4152.2844631346625
          },
          "nodeIndex": "SOURCE_SYSTEM",
          "nodeLineageTag": "3f0eddf9-f508-4e9d-90cd-79ffc066b836",
          "size": {
            "height": 300,
            "width": 234
          },
          "zIndex": 0
        },
        {
          "location": {
            "x": 632.67821410391025,
            "y": 3225.7373445737612
          },
          "nodeIndex": "SOURCE_SYSTEM_STATUS",
          "nodeLineageTag": "28829de7-93ba-4e8c-89bf-19259f711d30",
          "size": {
            "height": 300,
            "width": 234
          },
          "zIndex": 0
        },
        {
          "location": {
            "x": 1052.0469067404965,
            "y": 3229.663328945825
          },
          "nodeIndex": "TRANSACTION",
          "nodeLineageTag": "a738f40b-4cc9-45fd-8e3d-b30631e68dc2",
          "size": {
            "height": 300,
            "width": 234
          },
          "zIndex": 0
        }
      ],
      "name": "All tables",
      "zoomValue": 100,
      "pinKeyFieldsToTop": false,
      "showExtraHeaderInfo": false,
      "hideKeyFieldsWhenCollapsed": false,
      "tablesLocked": false
    }
  ],
  "selectedDiagram": "All tables",
  "defaultDiagram": "All tables"
}